{
  "rgbw_par": {
    "name": "RGBW PAR",
    "manufacturer": "Generic",
    "channels": [
      {
        "index": 0,
        "name": "red",
        "type": "color",
        "range": [
          0,
          255
        ]
      },
      {
        "index": 1,
        "name": "green",
        "type": "color",
        "range": [
          0,
          255
        ]
      },
      {
        "index": 2,
        "name": "blue",
        "type": "color",
        "range": [
          0,
          255
        ]
      },
      {
        "index": 3,
        "name": "white",
        "type": "color",
        "range": [
          0,
          255
        ]
      }
    ]
  },
  "rgbw_dimmer_shutter_macro": {
    "name": "Generic PAR (RGBW + Dimmer/Shutter/Macro)",
    "manufacturer": "Generic",
    "channels": [
      {
        "index": 0,
        "name": "dimmer",
        "type": "dimmer",
        "range": [
          0,
          255
        ]
      },
      {
        "index": 1,
        "name": "red",
        "type": "color",
        "range": [
          0,
          255
        ]
      },
      {
        "index": 2,
        "name": "green",
        "type": "color",
        "range": [
          0,
          255
        ]
      },
      {
        "index": 3,
        "name": "blue",
        "type": "color",
        "range": [
          0,
          255
        ]
      },
      {
        "index": 4,
        "name": "white",
        "type": "color",
        "range": [
          0,
          255
        ]
      },
      {
        "index": 5,
        "name": "shutter",
        "type": "other",
        "range": [
          0,
          255
        ]
      },
      {
        "index": 6,
        "name": "macro",
        "type": "other",
        "range": [
          0,
          255
        ]
      },
      {
        "index": 7,
        "name": "macro_speed",
        "type": "other",
        "range": [
          0,
          255
        ]
      }
    ]
  },
  "uking_mini_moving_light": {
    "name": "Moving Head 60W",
    "channels": [
      {
        "index": 0,
        "name": "pan",
        "type": "pan",
        "range": [
          0,
          255
        ]
      },
      {
        "index": 1,
        "name": "pan_fine",
        "type": "pan_fine",
        "range": [
          0,
          255
        ]
      },
      {
        "index": 2,
        "name": "tilt",
        "type": "tilt",
        "range": [
          0,
          255
        ]
      },
      {
        "index": 3,
        "name": "tilt_fine",
        "type": "tilt_fine",
        "range": [
          0,
          255
        ]
      },
      {
        "index": 4,
        "name": "color_wheel",
        "type": "other",
        "range": [
          0,
          255
        ]
      },
      {
        "index": 5,
        "name": "gobo_wheel",
        "type": "other",
        "range": [
          0,
          255
        ]
      },
      {
        "index": 6,
        "name": "strobe",
        "type": "shutter",
        "range": [
          0,
          255
        ]
      },
      {
        "index": 7,
        "name": "master_dimmer",
        "type": "dimmer",
        "range": [
          0,
          255
        ]
      },
      {
        "index": 8,
        "name": "pan_tilt_speed",
        "type": "speed",
        "range": [
          0,
          255
        ]
      },
      {
        "index": 9,
        "name": "auto_sound_mode",
        "type": "other",
        "range": [
          0,
          255
        ]
      },
      {
        "index": 10,
        "name": "reset",
        "type": "other",
        "range": [
          0,
          255
        ]
      }
    ],
    "manufacturer": "U-King",
    "dimmer_on_black": true,
    "color_wheel_mapping": {
      "white": 5,
      "red": 15,
      "green": 25,
      "blue": 35,
      "yellow": 45,
      "orange": 55,
      "cyan": 65,
      "magenta": 75
    }
  },
  "dd_01": {
    "name": "Roto",
    "channels": [
      {
        "index": 0,
        "name": "speed",
        "type": "speed",
        "range": [
          0,
          255
        ]
      },
      {
        "index": 1,
        "name": "direction",
        "type": "other",
        "range": [
          0,
          255
        ]
      }
    ],
    "manufacturer": "DiscoDriver"
  }
}